waylay/services/registry/models/__init__.py
waylay/services/registry/models/active_event_data.py
waylay/services/registry/models/active_event_sse.py
waylay/services/registry/models/active_event_sse_event.py
waylay/services/registry/models/alt_embedded_version_i_kfserving_response_v2.py
waylay/services/registry/models/alt_embedded_version_i_plug_response_v2.py
waylay/services/registry/models/alt_embedded_version_i_webscript_response_with_invoke_link_v2.py
waylay/services/registry/models/alt_version_hal_link.py
waylay/services/registry/models/alt_version_hal_link_draft.py
waylay/services/registry/models/alt_version_hal_link_published.py
waylay/services/registry/models/any_job_for_function.py
waylay/services/registry/models/any_job_result.py
waylay/services/registry/models/any_job_status.py
waylay/services/registry/models/any_job_status_summary.py
waylay/services/registry/models/archive_format.py
waylay/services/registry/models/archive_format_exclude.py
waylay/services/registry/models/archive_format_filter.py
waylay/services/registry/models/asset_condition.py
waylay/services/registry/models/asset_condition_content_type.py
waylay/services/registry/models/asset_condition_pattern.py
waylay/services/registry/models/asset_role.py
waylay/services/registry/models/asset_summary_with_hal_link.py
waylay/services/registry/models/asset_summary_with_hal_link_links.py
waylay/services/registry/models/assets_conditions.py
waylay/services/registry/models/batch.py
waylay/services/registry/models/batch_args.py
waylay/services/registry/models/batch_job_status.py
waylay/services/registry/models/batch_job_status_type.py
waylay/services/registry/models/batch_result.py
waylay/services/registry/models/build.py
waylay/services/registry/models/build1.py
waylay/services/registry/models/build_args.py
waylay/services/registry/models/build_job_status.py
waylay/services/registry/models/build_result.py
waylay/services/registry/models/build_spec.py
waylay/services/registry/models/build_type.py
waylay_sdk_registry_types-2.17.1.20241025.dist-info/LICENSE.txt
waylay_sdk_registry_types-2.17.1.20241025.dist-info/METADATA
waylay_sdk_registry_types-2.17.1.20241025.dist-info/WHEEL
waylay_sdk_registry_types-2.17.1.20241025.dist-info/top_level.txt
waylay_sdk_registry_types-2.17.1.20241025.dist-info/RECORD
